{
    "chart": {
        "caption": "",
        "subCaption": "",
        "yAxisName": "",
        "numberPrefix": "",
        "paletteColors": "#0075c2",
        "bgColor": "#ffffff",
        "showBorder": "0",
        "showCanvasBorder": "0",
        "usePlotGradientColor": "0",
        "plotBorderAlpha": "10",
        "placeValuesInside": "1",
        "valueFontColor": "#ffffff",
        "showAxisLines": "0",
        "axisLineAlpha": "0",
        "divLineAlpha": "0",
        "alignCaptionWithCanvas": "0",
        "showAlternateVGridColor": "0",
        "captionFontSize": "14",
        "subcaptionFontSize": "14",
        "subcaptionFontBold": "0",
        "toolTipColor": "#ffffff",
        "toolTipBorderThickness": "0",
        "toolTipBgColor": "#000000",
        "toolTipBgAlpha": "80",
        "toolTipBorderRadius": "2",
        "toolTipPadding": "5",
        "showYAxisValues": "0"
    },

    "data": [
        {
            "value": "684"
        },
        {

            "value": "501"
        },
        {

            "value": "337"
        },
        {

            "value": "87"
        },
        {

            "value": "96"
        }
    ]
}
